garpar/__init__.py
garpar/constants.py
garpar/garpar_io.py
garpar/core/__init__.py
garpar/core/coercer_mixin.py
garpar/core/covcorr_acc.py
garpar/core/div_acc.py
garpar/core/ereturns_acc.py
garpar/core/plot_acc.py
garpar/core/prices_acc.py
garpar/core/risk_acc.py
garpar/core/stocks_set.py
garpar/core/utilities_acc.py
garpar/datasets/__init__.py
garpar/datasets/ds_base.py
garpar/datasets/multisector.py
garpar/datasets/risso.py
garpar/datasets/data/__init__.py
garpar/datasets/data/merval.csv
garpar/optimize/__init__.py
garpar/optimize/mean_variance.py
garpar/optimize/opt_base.py
garpar/utils/__init__.py
garpar/utils/accabc.py
garpar/utils/bunch.py
garpar/utils/context.py
garpar/utils/entropy.py
garpar/utils/mabc.py
garpar/utils/scalers.py
garpar/utils/unames.py
garpar-1.5.0.dev1.dist-info/LICENSE.txt
garpar-1.5.0.dev1.dist-info/METADATA
garpar-1.5.0.dev1.dist-info/WHEEL
garpar-1.5.0.dev1.dist-info/top_level.txt
garpar-1.5.0.dev1.dist-info/RECORD
