Metadata-Version: 2.2
Name: garpar
Version: 1.5.0.dev1
Summary: Generation and Analysis of Real and Artificial Portfolio Returns
Author-email: Diego N Gimenez Irusta <d.gimenez0101@unc.edu.ar>, Nadia A Luczywo <nadia.luczywo@unc.edu.ar>, Juan B Cabral <jbcabral@unc.edu.ar>
License: MIT License
Project-URL: Homepage, https://garpar.quatrope.org/
Project-URL: Repository, https://github.com/quatrope/garpar
Keywords: market simulation,informational efficiency,portfolio optimization
Classifier: Development Status :: 5 - Production/Stable
Classifier: Intended Audience :: Education
Classifier: Intended Audience :: Science/Research
Classifier: License :: OSI Approved :: MIT License
Classifier: Operating System :: OS Independent
Classifier: Programming Language :: Python
Classifier: Programming Language :: Python :: 3.10
Classifier: Programming Language :: Python :: 3.11
Classifier: Programming Language :: Python :: 3.12
Classifier: Programming Language :: Python :: 3.13
Classifier: Programming Language :: Python :: Implementation :: CPython
Classifier: Topic :: Scientific/Engineering
Classifier: Topic :: Office/Business :: Financial
License-File: LICENSE.txt
Requires-Dist: attrs>=23.2.0
Requires-Dist: build>=1.2.1
Requires-Dist: h5py>=3.11.0
Requires-Dist: importlib_metadata
Requires-Dist: numpy>=2.2.0
Requires-Dist: pyportfolioopt>=1.5.0
Requires-Dist: scikit-learn>=1.6.0
Requires-Dist: seaborn>=0.13.0
Requires-Dist: pandas>=2.2.0
